py4N_gram/__init__.py
py4N_gram/tokenize.py
py4N_gram-0.0.1.dist-info/METADATA
py4N_gram-0.0.1.dist-info/WHEEL
py4N_gram-0.0.1.dist-info/top_level.txt
py4N_gram-0.0.1.dist-info/RECORD
